README.md
setup.py
bin/test_video_pkg.py
template_python_projects.egg-info/PKG-INFO
template_python_projects.egg-info/SOURCES.txt
template_python_projects.egg-info/dependency_links.txt
template_python_projects.egg-info/top_level.txt
video/__init__.py
video/players/__init__.py
video/players/mp4play.py