Metadata-Version: 1.0
Name: template-python-projects
Version: 1.5
Summary: Template Project in Python
Home-page: https://pypi.org/project/template_python_projects
Author: djclavero
Author-email: djclavero@yahoo.com
License: MIT
Keywords: projects,python
Platform: UNKNOWN
